{"name":"As a user I have to be able registration","id":"register;as-a-user-i-have-to-be-able-registration","testSteps":[{"number":1,"description":"Given I am on the register page","duration":10332,"startTime":"2022-05-16T00:35:16.169651100+07:00[Asia/Jakarta]","screenshots":[{"screenshot":"0ba6e8bb0dbd98adfe749502cc48ff0da377cd7b0172f40fe1ccbac8137b3703.png","timeStamp":1652636126502}],"result":"SUCCESS","precondition":false,"level":0,"children":[{"number":2,"description":"Open url","duration":9986,"startTime":"2022-05-16T00:35:16.247774100+07:00[Asia/Jakarta]","screenshots":[{"screenshot":"0ba6e8bb0dbd98adfe749502cc48ff0da377cd7b0172f40fe1ccbac8137b3703.png","timeStamp":1652636126234}],"result":"SUCCESS","precondition":false,"level":1},{"number":3,"description":"Validate on register page","duration":249,"startTime":"2022-05-16T00:35:26.236642200+07:00[Asia/Jakarta]","screenshots":[{"screenshot":"0ba6e8bb0dbd98adfe749502cc48ff0da377cd7b0172f40fe1ccbac8137b3703.png","timeStamp":1652636126244},{"screenshot":"0ba6e8bb0dbd98adfe749502cc48ff0da377cd7b0172f40fe1ccbac8137b3703.png","timeStamp":1652636126486}],"result":"SUCCESS","precondition":false,"level":1}]},{"number":4,"description":"When I input valid fullname","duration":799,"startTime":"2022-05-16T00:35:26.502146400+07:00[Asia/Jakarta]","screenshots":[{"screenshot":"2c08c2d731b287a2c025af6008e44039ecca83a5f373b84906341764ccf9f872.png","timeStamp":1652636127301}],"result":"SUCCESS","precondition":false,"level":0,"children":[{"number":5,"description":"Input fullname: Dwi Ernawati","duration":790,"startTime":"2022-05-16T00:35:26.502146400+07:00[Asia/Jakarta]","screenshots":[{"screenshot":"2c08c2d731b287a2c025af6008e44039ecca83a5f373b84906341764ccf9f872.png","timeStamp":1652636127292}],"result":"SUCCESS","precondition":false,"level":1}]},{"number":6,"description":"And I input valid email","duration":1087,"startTime":"2022-05-16T00:35:27.302198300+07:00[Asia/Jakarta]","screenshots":[{"screenshot":"0c8c8b22a047c71d6518931821acecfd49ecc9474c842c23c695dfaa9950d4e2.png","timeStamp":1652636128389}],"result":"SUCCESS","precondition":false,"level":0,"children":[{"number":7,"description":"Input email: 195410079dwiernawati@gmail.com","duration":1068,"startTime":"2022-05-16T00:35:27.312192300+07:00[Asia/Jakarta]","screenshots":[{"screenshot":"0c8c8b22a047c71d6518931821acecfd49ecc9474c842c23c695dfaa9950d4e2.png","timeStamp":1652636128380}],"result":"SUCCESS","precondition":false,"level":1}]},{"number":8,"description":"And I input valid password","duration":702,"startTime":"2022-05-16T00:35:28.391744200+07:00[Asia/Jakarta]","screenshots":[{"screenshot":"ecdc8486c35f934515a642b80e3727322d742ec8b1f8a089497f8c7934c45573.png","timeStamp":1652636129094}],"result":"SUCCESS","precondition":false,"level":0,"children":[{"number":9,"description":"Input password: September90*","duration":688,"startTime":"2022-05-16T00:35:28.399069500+07:00[Asia/Jakarta]","screenshots":[{"screenshot":"ecdc8486c35f934515a642b80e3727322d742ec8b1f8a089497f8c7934c45573.png","timeStamp":1652636129087}],"result":"SUCCESS","precondition":false,"level":1}]},{"number":10,"description":"And click register button","duration":634,"startTime":"2022-05-16T00:35:29.095659900+07:00[Asia/Jakarta]","screenshots":[{"screenshot":"2f91b39d6145003bf98cb9e2f4c035b18a97c95bb068e7acb2f9183833835e12.png","timeStamp":1652636129730}],"result":"SUCCESS","precondition":false,"level":0,"children":[{"number":11,"description":"Click register button","duration":616,"startTime":"2022-05-16T00:35:29.106651100+07:00[Asia/Jakarta]","screenshots":[{"screenshot":"2f91b39d6145003bf98cb9e2f4c035b18a97c95bb068e7acb2f9183833835e12.png","timeStamp":1652636129722}],"result":"SUCCESS","precondition":false,"level":1}]},{"number":12,"description":"Then I go to login page","duration":951,"startTime":"2022-05-16T00:35:29.731200200+07:00[Asia/Jakarta]","screenshots":[{"screenshot":"5279a2677f51cd42d80df4d0bf105786ca0efdec9c31dd310d9911ecf03761b4.png","timeStamp":1652636130682}],"result":"SUCCESS","precondition":false,"level":0}],"userStory":{"id":"register","storyName":"register","displayName":"register","path":"Register.feature","narrative":"  As a user\n  I want to registration\n  So that I can login","type":"feature"},"featureTag":{"name":"register","type":"feature","displayName":"register"},"title":"As a user I have to be able registration","description":"","tags":[{"name":"register","type":"feature","displayName":"register"}],"startTime":"2022-05-16T00:35:16.154027300+07:00[Asia/Jakarta]","duration":14530,"projectKey":"","sessionId":"6f60c876790d6bc6bb65196d95f3fff6","driver":"chrome","isManualTestingUpToDate":false,"manual":false,"testSource":"Cucumber","result":"SUCCESS"}